cpm_kernels/__init__.py
cpm_kernels/device/__init__.py
cpm_kernels/kernels/__init__.py
cpm_kernels/kernels/arith.py
cpm_kernels/kernels/base.py
cpm_kernels/kernels/embedding.py
cpm_kernels/kernels/gelu.py
cpm_kernels/kernels/gemm.py
cpm_kernels/kernels/gemv.py
cpm_kernels/kernels/layernorm.py
cpm_kernels/kernels/mask.py
cpm_kernels/kernels/position_bucket.py
cpm_kernels/kernels/softmax.py
cpm_kernels/kernels/transpose.py
cpm_kernels/kernels/utils.py
cpm_kernels/kernels/cuda/arith.fatbin
cpm_kernels/kernels/cuda/embedding.fatbin
cpm_kernels/kernels/cuda/gelu.fatbin
cpm_kernels/kernels/cuda/gemm.fatbin
cpm_kernels/kernels/cuda/gemv.fatbin
cpm_kernels/kernels/cuda/layernorm.fatbin
cpm_kernels/kernels/cuda/mask.fatbin
cpm_kernels/kernels/cuda/position_bucket.fatbin
cpm_kernels/kernels/cuda/softmax.fatbin
cpm_kernels/kernels/cuda/transpose.fatbin
cpm_kernels/kernels/cuda/utils.fatbin
cpm_kernels/library/__init__.py
cpm_kernels/library/base.py
cpm_kernels/library/cublaslt.py
cpm_kernels/library/cuda.py
cpm_kernels/library/cudart.py
cpm_kernels/library/nvrtc.py
cpm_kernels/torch/__init__.py
cpm_kernels/torch/arith.py
cpm_kernels/torch/embedding.py
cpm_kernels/torch/gelu.py
cpm_kernels/torch/gemm.py
cpm_kernels/torch/layernorm.py
cpm_kernels/torch/mask.py
cpm_kernels/torch/position_embedding.py
cpm_kernels/torch/softmax.py
cpm_kernels/torch/transpose.py
cpm_kernels/torch/utils.py
cpm_kernels-1.0.10.dist-info/LICENSE
cpm_kernels-1.0.10.dist-info/METADATA
cpm_kernels-1.0.10.dist-info/WHEEL
cpm_kernels-1.0.10.dist-info/top_level.txt
cpm_kernels-1.0.10.dist-info/RECORD
